planettapper/__init__.py
planettapper/celestialbodies.py
planettapper/search.py
planettapper-0.1.2.dist-info/LICENSE
planettapper-0.1.2.dist-info/METADATA
planettapper-0.1.2.dist-info/WHEEL
planettapper-0.1.2.dist-info/RECORD
