Metadata-Version: 2.3
Name: planettapper
Version: 0.1.2
Summary: 
Author: Danny Levinstein
Requires-Python: >=3.11
Classifier: Programming Language :: Python :: 3
Classifier: Programming Language :: Python :: 3.11
Classifier: Programming Language :: Python :: 3.12
Classifier: Programming Language :: Python :: 3.13
Requires-Dist: pandas (>=2.3.1,<3.0.0)
Requires-Dist: pyvo (>=1.7,<2.0)
